adept_augmentations/__init__.py
adept_augmentations/analyzers/__init__.py
adept_augmentations/analyzers/analyzer.py
adept_augmentations/augmenters/__init__.py
adept_augmentations/augmenters/augmenter.py
adept_augmentations/augmenters/constants.py
adept_augmentations/augmenters/extractors.py
adept_augmentations/profilers/__init__.py
adept_augmentations/utils.py
adept_augmentations-0.1.1.dist-info/LICENSE
adept_augmentations-0.1.1.dist-info/WHEEL
adept_augmentations-0.1.1.dist-info/METADATA
adept_augmentations-0.1.1.dist-info/RECORD
